[
  {
    "anonymous": false,
    "inputs": [
      {
        "components": [
          {
            "internalType": "address",
            "name": "facetAddress",
            "type": "address"
          },
          {
            "internalType": "string",
            "name": "facetName",
            "type": "string"
          },
          {
            "internalType": "string[]",
            "name": "functionSignatures",
            "type": "string[]"
          }
        ],
        "indexed": false,
        "internalType": "struct IDiamondCut.FacetCut[]",
        "name": "_diamondCut",
        "type": "tuple[]"
      },
      {
        "indexed": false,
        "internalType": "address",
        "name": "_init",
        "type": "address"
      },
      {
        "indexed": false,
        "internalType": "bytes",
        "name": "_calldata",
        "type": "bytes"
      }
    ],
    "name": "DiamondCut",
    "type": "event"
  },
  {
    "inputs": [
      {
        "components": [
          {
            "internalType": "address",
            "name": "facetAddress",
            "type": "address"
          },
          {
            "internalType": "string",
            "name": "facetName",
            "type": "string"
          },
          {
            "internalType": "string[]",
            "name": "functionSignatures",
            "type": "string[]"
          }
        ],
        "internalType": "struct IDiamondCut.FacetCut[]",
        "name": "_diamondCut",
        "type": "tuple[]"
      },
      {
        "internalType": "address",
        "name": "_init",
        "type": "address"
      },
      {
        "internalType": "bytes",
        "name": "_calldata",
        "type": "bytes"
      }
    ],
    "name": "diamondCut",
    "outputs": [],
    "stateMutability": "nonpayable",
    "type": "function"
  }
]
